{
  "greeting": "Hola",
  "name": "Ronnie",
  "greetingText": "You are awesome, creative, beautiful and upm everyday!",
  "wishText": "May you keep reciting your poems and keep explaining this silly all the things ;)",
  "imagePath": "img/ron2.png",
  "text1": "It's your birthday!!! :D",
  "textInChatBox": "Happy birthday to you!! Yayyayayay! You are the best blah...",
  "sendButtonLabel": "Send",
  "text2": "That's what I was going to do.",
  "text3": "But then I stopped.",
  "text4": "I realised, I wanted to do something",
  "text4Adjective": "special",
  "text5Entry": "Because,",
  "text5Content": "You are Special",
  "smiley": ":)",
  "bigTextPart1": "S",
  "bigTextPart2": "O",
  "wishHeading": "Happy Birthday!",
  "outroText": "Okay, now enjoy your day, and make it the best while sliding to the new decade :]",
  "replayText": "Or click, if you want to watch it again, be eepy!",
  "outroSmiley": ":)"
}
